adoniram/SharedKit.py
adoniram/__init__.py
adoniram/config/__init__.py
adoniram/config/config.py
adoniram/config/config.sample.py
adoniram/distributor/AdoniramDistributorCommander.py
adoniram/distributor/AdoniramDistributorServer.py
adoniram/distributor/ProcessorRegistration.py
adoniram/distributor/__init__.py
adoniram/exception/BadMessageError.py
adoniram/exception/HandleMessageError.py
adoniram/exception/ProcessorConnectionLost.py
adoniram/exception/ProcessorNameConflictError.py
adoniram/exception/ProcessorNotRegisteredError.py
adoniram/exception/ProcessorRegistrationLocked.py
adoniram/exception/ServerConnectionLost.py
adoniram/exception/__init__.py
adoniram/message/BaseMessage.py
adoniram/message/BaseRequestMessage.py
adoniram/message/BaseResponseMessage.py
adoniram/message/__init__.py
adoniram/message/request/RequestMessageAsHandleTask.py
adoniram/message/request/RequestMessageAsPing.py
adoniram/message/request/RequestMessageAsRegisterProcessor.py
adoniram/message/request/RequestMessageAsSeekTaskToHandle.py
adoniram/message/request/RequestMessageAsShutdownServer.py
adoniram/message/request/RequestMessageAsUnregisterProcessor.py
adoniram/message/request/__init__.py
adoniram/message/response/ResponseMessageAsDone.py
adoniram/message/response/ResponseMessageAsRequestFormatError.py
adoniram/message/response/ResponseMessageAsRequestHandleError.py
adoniram/message/response/__init__.py
adoniram/processor/AdoniramProcesserClient.py
adoniram/processor/__init__.py
adoniram/task/BaseTaskHandler.py
adoniram/task/BaseTaskSeeker.py
adoniram/task/__init__.py
adoniram-0.0.6.dist-info/LICENSE
adoniram-0.0.6.dist-info/METADATA
adoniram-0.0.6.dist-info/WHEEL
adoniram-0.0.6.dist-info/top_level.txt
adoniram-0.0.6.dist-info/RECORD
