Metadata-Version: 2.1
Name: adoniram
Version: 0.0.6
Summary: A Server-Client Communication Framework
Home-page: https://github.com/sinri/Adoniram
Author: Sinri Edogawa
Author-email: e.joshua.s.e@gmail.com
License: MIT
Platform: UNKNOWN
Classifier: Programming Language :: Python :: 3
Classifier: License :: OSI Approved :: GNU General Public License v3 or later (GPLv3+)
Classifier: Operating System :: POSIX
Classifier: Operating System :: MacOS :: MacOS X
Requires-Python: >=3.8
License-File: LICENSE
Requires-Dist: nehushtan (~=0.4.18)
